LICENSE
MANIFEST.in
README.rst
pavement.py
requirements.txt
setup.py
docs/api.rst
docs/index.rst
docs/install.rst
docs/running.rst
docs/api/namespace.rst
docs/api/render.rst
docs/api/tools.rst
pageit/__init__.py
pageit/__init__.pyc
pageit/namespace.py
pageit/namespace.pyc
pageit/render.py
pageit/render.pyc
pageit/tools.py
pageit/tools.pyc
pageit.egg-info/PKG-INFO
pageit.egg-info/SOURCES.txt
pageit.egg-info/dependency_links.txt
pageit.egg-info/entry_points.txt
pageit.egg-info/requires.txt
pageit.egg-info/top_level.txt
scripts/pageit
scripts/pageit.bat
test/TestMako.py
test/TestPageit.py
test/TestWatch.py
test/__init__.py