Metadata-Version: 1.1
Name: pageit
Version: 0.2.3
Summary: pageit: static html generator
Home-page: https://github.com/metaist/pageit
Author: The Metaist
Author-email: metaist@metaist.com
License: MIT
Download-URL: https://github.com/metaist/pageit
Keywords: static website generator
Platform: UNKNOWN
Classifier: Development Status :: 4 - Beta
Classifier: Environment :: Console
Classifier: Intended Audience :: Developers
Classifier: License :: OSI Approved :: MIT License
Classifier: Natural Language :: English
Classifier: Operating System :: OS Independent
Classifier: Programming Language :: Python :: 2
Classifier: Topic :: Software Development :: Libraries
Provides: pageit
